pollect/Pollect.py
pollect/Requirements.py
pollect/__init__.py
pollect/core/Core.py
pollect/core/ExecutionScheduler.py
pollect/core/Factories.py
pollect/core/Helper.py
pollect/core/Log.py
pollect/core/OSEnv.py
pollect/core/ValueCache.py
pollect/core/ValueSet.py
pollect/core/__init__.py
pollect/core/config/ConfigContainer.py
pollect/core/config/__init__.py
pollect/core/events/Event.py
pollect/core/events/__init__.py
pollect/libs/DependencyResolver.py
pollect/libs/Units.py
pollect/libs/Utils.py
pollect/libs/__init__.py
pollect/libs/api/Serializable.py
pollect/libs/api/__init__.py
pollect/libs/google/AppConfig.py
pollect/libs/google/FileProvider.py
pollect/libs/google/GcsBackend.py
pollect/libs/google/Helper.py
pollect/libs/google/MetricsData.py
pollect/libs/google/StatsParser.py
pollect/libs/google/__init__.py
pollect/libs/google/metrics/AppVersionMetrics.py
pollect/libs/google/metrics/__init__.py
pollect/libs/google/parser/AppVersionParser.py
pollect/libs/google/parser/__init__.py
pollect/libs/modbus/__init__.py
pollect/libs/sma/SmaEnergyMeter.py
pollect/libs/sma/SmaModbus.py
pollect/libs/sma/__init__.py
pollect/libs/viessmann/ViessmannApi.py
pollect/libs/viessmann/__init__.py
pollect/libs/zodiac/Models.py
pollect/libs/zodiac/ZodiacApi.py
pollect/libs/zodiac/__init__.py
pollect/sources/AppStoreConnectSource.py
pollect/sources/BindSource.py
pollect/sources/CertificateSource.py
pollect/sources/DiskUsageSource.py
pollect/sources/DummySource.py
pollect/sources/EspHomeSource.py
pollect/sources/EvccSource.py
pollect/sources/FritzSource.py
pollect/sources/GdcSource.py
pollect/sources/HomematicIpSource.py
pollect/sources/HttpIngressSource.py
pollect/sources/HttpSource.py
pollect/sources/IOSource.py
pollect/sources/InterfaceSource.py
pollect/sources/K8sNamespaceTrafficSource.py
pollect/sources/MMISource.py
pollect/sources/MemoryUsageSource.py
pollect/sources/OpenhabSource.py
pollect/sources/PlexSource.py
pollect/sources/PmccSource.py
pollect/sources/ProcessSource.py
pollect-1.2.2.dist-info/LICENSE
pollect-1.2.2.dist-info/METADATA
pollect-1.2.2.dist-info/WHEEL
pollect-1.2.2.dist-info/entry_points.txt
pollect-1.2.2.dist-info/top_level.txt
pollect-1.2.2.dist-info/RECORD
