Metadata-Version: 2.2
Name: pollect
Version: 1.2.2
Summary: Metrics collection daemon and exporter
Home-page: https://github.com/davidgiga1993/pollect
Author: davidgiga1993
Author-email: david@dev-core.org
Classifier: Development Status :: 4 - Beta
Classifier: Programming Language :: Python :: 3
Classifier: License :: OSI Approved :: MIT License
Classifier: Operating System :: OS Independent
Requires-Python: >3.6
License-File: LICENSE
Requires-Dist: schedule
Requires-Dist: prometheus-client
Requires-Dist: PyYAML
Requires-Dist: requests
Dynamic: author
Dynamic: author-email
Dynamic: classifier
Dynamic: description
Dynamic: description-content-type
Dynamic: home-page
Dynamic: requires-dist
Dynamic: requires-python
Dynamic: summary
